LICENSE.txt
MANIFEST.in
README.md
requirements.txt
setup.cfg
setup.py
bin/obscmd
bin/obscmd.cmd
bin/obscmd_bash_completer
bin/obscmd_completer
bin/obscmd_zsh_completer.sh
obs/__init__.py
obs/auth.py
obs/bucket.py
obs/client.py
obs/cloghandler.py
obs/const.py
obs/convertor.py
obs/ilog.py
obs/model.py
obs/portalocker.py
obs/transfer.py
obs/util.py
obscmd/__init__.py
obscmd/__main__.py
obscmd/argparser.py
obscmd/arguments.py
obscmd/clidriver.py
obscmd/commands.py
obscmd/compat.py
obscmd/completer.py
obscmd/config.py
obscmd/configloader.py
obscmd/constant.py
obscmd/exceptions.py
obscmd/globl.py
obscmd/model.py
obscmd/multithreading.py
obscmd/schema.py
obscmd/testutils.py
obscmd/utils.py
obscmd.egg-info/PKG-INFO
obscmd.egg-info/SOURCES.txt
obscmd.egg-info/dependency_links.txt
obscmd.egg-info/requires.txt
obscmd.egg-info/top_level.txt
obscmd/cmds/__init__.py
obscmd/cmds/commands.py
obscmd/cmds/configure/__init__.py
obscmd/cmds/configure/cmd.py
obscmd/cmds/obs/__init__.py
obscmd/cmds/obs/cmd.py
obscmd/cmds/obs/obsutil.py
obscmd/cmds/obs/subcmd.py
obscmd/cmds/obs/transfer.py
obscmd/cmds/obs/subcmds/__init__.py
obscmd/cmds/obs/subcmds/cp.py
obscmd/cmds/obs/subcmds/infob.py
obscmd/cmds/obs/subcmds/ls.py
obscmd/cmds/obs/subcmds/mb.py
obscmd/cmds/obs/subcmds/mbacl.py
obscmd/cmds/obs/subcmds/mblc.py
obscmd/cmds/obs/subcmds/mblog.py
obscmd/cmds/obs/subcmds/mbp.py
obscmd/cmds/obs/subcmds/mbws.py
obscmd/cmds/obs/subcmds/rb.py
obscmd/cmds/obs/subcmds/rblc.py
obscmd/cmds/obs/subcmds/rbp.py
obscmd/cmds/obs/subcmds/rbws.py
obscmd/cmds/obs/subcmds/rm.py
obscmd/cmds/obs/subcmds/surl.py
obscmd/data/log.ini
obscmd/data/obscmd.ini