Metadata-Version: 1.0
Name: obscmd
Version: 5.0.0b0
Summary: Universal Command Line Environment for Huawei command.
Home-page: UNKNOWN
Author: huaweicloud
Author-email: UNKNOWN
License: Apache License 2.0
Platform: UNKNOWN
